peft_singlora/__init__.py
peft_singlora/config.py
peft_singlora/layer.py
peft_singlora-0.2.0.dist-info/licenses/LICENSE
peft_singlora-0.2.0.dist-info/METADATA
peft_singlora-0.2.0.dist-info/WHEEL
peft_singlora-0.2.0.dist-info/top_level.txt
peft_singlora-0.2.0.dist-info/RECORD
