Metadata-Version: 2.4
Name: peft-singlora
Version: 0.2.0
Summary: SingLoRA: Single Low-Rank Adaptation for PEFT
Author-email: bghira <bghira@users.github.com>
Maintainer-email: bghira <bghira@users.github.com>
License: BSD 2-Clause License
Project-URL: Homepage, https://github.com/bghira/PEFT-SingLoRA
Project-URL: Documentation, https://github.com/bghira/PEFT-SingLoRA#readme
Project-URL: Repository, https://github.com/bghira/PEFT-SingLoRA
Project-URL: Issues, https://github.com/bghira/PEFT-SingLoRA/issues
Keywords: peft,lora,singlora,fine-tuning,transformers,pytorch
Classifier: Development Status :: 3 - Alpha
Classifier: Intended Audience :: Developers
Classifier: Intended Audience :: Science/Research
Classifier: License :: OSI Approved :: BSD License
Classifier: Programming Language :: Python :: 3
Classifier: Programming Language :: Python :: 3.8
Classifier: Programming Language :: Python :: 3.9
Classifier: Programming Language :: Python :: 3.10
Classifier: Programming Language :: Python :: 3.11
Classifier: Programming Language :: Python :: 3.12
Classifier: Topic :: Scientific/Engineering :: Artificial Intelligence
Requires-Python: >=3.8
License-File: LICENSE
Requires-Dist: torch>=1.13.0
Requires-Dist: peft>=0.7.0
Requires-Dist: transformers>=4.34.0
Provides-Extra: dev
Requires-Dist: pytest>=7.0; extra == "dev"
Requires-Dist: pytest-cov>=4.0; extra == "dev"
Requires-Dist: black>=23.0; extra == "dev"
Requires-Dist: isort>=5.12; extra == "dev"
Requires-Dist: flake8>=6.0; extra == "dev"
Requires-Dist: mypy>=1.0; extra == "dev"
Provides-Extra: examples
Requires-Dist: datasets>=2.14.0; extra == "examples"
Requires-Dist: accelerate>=0.21.0; extra == "examples"
Requires-Dist: tqdm>=4.65.0; extra == "examples"
Dynamic: license-file
